leo_optimizer/__init__.py
leo_optimizer/admin.py
leo_optimizer/graphql.py
leo_optimizer-0.0.8.dist-info/LICENSE
leo_optimizer-0.0.8.dist-info/WHEEL
leo_optimizer-0.0.8.dist-info/METADATA
leo_optimizer-0.0.8.dist-info/RECORD
