Metadata-Version: 2.1
Name: leo-optimizer
Version: 0.0.8
Summary: Package for on fly optimizing SQL queries generated by Django ORM. This package targets the N+1 problem so well known to Django.
Home-page: https://github.com/LEO-Pharma-R-D-Data-Analytics/leo-optimizer
License: Apache-2.0
Keywords: graphql,graphene,django,N+1,optimizer
Author: Martin Andersen
Maintainer: Martin Andersen
Requires-Python: >=3.7,<4.0
Classifier: Intended Audience :: Developers
Classifier: License :: OSI Approved :: Apache Software License
Classifier: Programming Language :: Python :: 3
Classifier: Programming Language :: Python :: 3.10
Classifier: Programming Language :: Python :: 3.7
Classifier: Programming Language :: Python :: 3.8
Classifier: Programming Language :: Python :: 3.9
Classifier: Programming Language :: Python :: Implementation :: PyPy
Classifier: Topic :: Software Development :: Libraries
Requires-Dist: stringcase (>=1.2.0,<2.0.0)
Project-URL: Documentation, https://github.com/LEO-Pharma-R-D-Data-Analytics/leo-optimizer
Project-URL: Repository, https://github.com/LEO-Pharma-R-D-Data-Analytics/leo-optimizer
